{
  "usingComponents": {
    "van-button": "../../../static/vant/button/index",
    "van-row": "../../../static/vant/row/index",
    "van-col": "../../../static/vant/col/index",
    "van-cell": "../../../static/vant/cell/index",
    "van-cell-group": "../../../static/vant/cell-group/index",
    "van-icon": "../../../static/vant/icon/index",
    "van-popup": "../../../static/vant/popup/index",
    "van-transition": "../../../static/vant/transition/index",
    "van-checkbox": "../../../static/vant/checkbox/index",
    "van-checkbox-group": "../../../static/vant/checkbox-group/index",
    "van-field": "../../../static/vant/field/index",
    "van-radio": "../../../static/vant/radio/index",
    "van-radio-group": "../../../static/vant/radio-group/index",
    "van-search": "../../../static/vant/search/index",
    "van-slider": "../../../static/vant/slider/index",
    "van-stepper": "../../../static/vant/stepper/index",
    "van-switch": "../../../static/vant/switch/index",
    "van-switch-cell": "../../../static/vant/switch-cell/index",
    "van-action-sheet": "../../../static/vant/action-sheet/index",
    "van-dialog": "../../../static/vant/dialog/index",
    "van-loading": "../../../static/vant/loading/index",
    "van-swipe-cell": "../../../static/vant/swipe-cell/index",
    "van-toas": "../../../static/vant/toast/index",
    "van-notify": "../../../static/vant/notify/index",
    "van-notice-bar": "../../../static/vant/notice-bar/index",
    "van-panel": "../../../static/vant/panel/index",
    "van-progress": "../../../static/vant/progress/index",
    "van-steps": "../../../static/vant/steps/index",
    "van-tag": "../../../static/vant/tag/index",
    "van-tree-select": "../../../static/vant/tree-select/index",
    "van-badge": "../../../static/vant/badge/index",
    "van-badge-group": "../../../static/vant/badge-group/index",
    "van-nav-bar": "../../../static/vant/nav-bar/index",
    "van-tab": "../../../static/vant/tab/index",
    "van-tabs": "../../../static/vant/tabs/index",
    "van-tabbar": "../../../static/vant/tabbar/index",
    "van-tabbar-item": "../../../static/vant/tabbar-item/index",
    "van-area": "../../../static/vant/area/index",
    "van-card": "../../../static/vant/card/index",
    "van-submit-bar": "../../../static/vant/submit-bar/index",
    "van-goods-action": "../../../static/vant/goods-action/index",
    "van-goods-action-icon": "../../../static/vant/goods-action-icon/index",
    "van-goods-action-button": "../../../static/vant/goods-action-button/index"
  },
  "navigationBarTitleText": "农事需求"
}
